{"cameraMode":{"drawMode":0,"name":"Shaded","section":"Shading Mode"},"sceneLighting":true,"audioPlay":false,"sceneViewState":{"m_AlwaysRefresh":false,"showFog":true,"showSkybox":true,"showFlares":true,"showImageEffects":true,"showParticleSystems":true,"showVisualEffectGraphs":true,"m_FxEnabled":true},"in2DMode":false,"pivot":{"x":723.9240112304688,"y":387.7055358886719,"z":131.6119384765625},"rotation":{"x":0.021897001191973687,"y":-0.0026858048513531687,"z":0.00005650344610330649,"w":0.9997627139091492},"size":450.9259338378906,"orthographic":false}